VERSION
config/config.yaml
plato_client/__init__.py
plato_client/api/sessions.py
plato_client/api/users.py
plato_client/client.py
plato_client/core/__init__.py
plato_client/core/auth.py
plato_client/core/connection/__init__.py
plato_client/core/connection/broker.py
plato_client/core/image/__init__.py
plato_client/core/image/exception.py
plato_client/core/image/imageservice.py
plato_client/core/models.py
plato_client/core/plato_langchain.py
plato_client/core/plato_logger.py
plato_client/core/text/__init__.py
plato_client/core/text/exception.py
plato_client/core/text/textservice.py
plato_client/integration/__init__.py
plato_client/integration/langchain/__init__.py
plato_client/integration/langchain/chat_model.py
plato_client/logging.ini
plato_client-1.0.0.dist-info/METADATA
plato_client-1.0.0.dist-info/WHEEL
plato_client-1.0.0.dist-info/RECORD
