Metadata-Version: 2.1
Name: plato-client
Version: 1.0.0
Summary: Plato Client
Author: Vaibhav Singh
Author-email: vaibhav.singh@bain.com
Requires-Python: >=3.10,<4.0
Classifier: Programming Language :: Python :: 3
Classifier: Programming Language :: Python :: 3.10
Classifier: Programming Language :: Python :: 3.11
Requires-Dist: deprecated (==1.2.14)
Requires-Dist: envyaml (==1.10.211231)
Requires-Dist: fastapi (==0.100.0)
Requires-Dist: httpx (==0.24.1)
Requires-Dist: langchain (==0.0.271)
Requires-Dist: passlib[bcrypt] (==1.7.4)
Requires-Dist: pydantic (==1.10.9)
Requires-Dist: python-dotenv (==1.0.0)
Requires-Dist: python-jose (==3.3.0)
Requires-Dist: python-json-logger (==2.0.7)
Requires-Dist: python-multipart (==0.0.6)
Requires-Dist: pyyaml (==6.0)
Requires-Dist: requests (==2.31.0)
Requires-Dist: uvicorn (==0.22.0)
